[
  {
    "id": 3,
    "name": "Alec Howard",
    "email": "Donec.elementum@scelerisquescelerisquedui.net",
    "phone": "00000004"
  },
  {
    "id": 4,
    "name": "Alec Howard",
    "email": "Donec.elementum@scelerisquescelerisquedui.net",
    "phone": "00000004"
  },
  {
    "id": 5,
    "name": "Alec Howard",
    "email": "Donec.elementum@scelerisquescelerisquedui.net",
    "phone": "00000004"
  },
  {
    "id": 6,
    "name": "Alec Howard",
    "email": "Donec.elementum@scelerisquescelerisquedui.net",
    "phone": "00000004"
  },
  {
    "id": 7,
    "name": "Alec Howard",
    "email": "Donec.elementum@scelerisquescelerisquedui.net",
    "phone": "00000004"
  },
  {
    "id": 8,
    "name": "Alec Howard",
    "email": "Donec.elementum@scelerisquescelerisquedui.net",
    "phone": "00000004"
  },
  {
    "id": 9,
    "name": "Alec Howard",
    "email": "Donec.elementum@scelerisquescelerisquedui.net",
    "phone": "00000004"
  },
  {
    "id": 10,
    "name": "Alec Howard",
    "email": "Donec.elementum@scelerisquescelerisquedui.net",
    "phone": "00000004"
  },
  {
    "id": 11,
    "name": "Alec Howard",
    "email": "Donec.elementum@scelerisquescelerisquedui.net",
    "phone": "00000004"
  },
  {
    "id": 12,
    "name": "Alec Howard",
    "email": "Donec.elementum@scelerisquescelerisquedui.net",
    "phone": "00000004"
  },
  {
    "id": 13,
    "name": "Alec Howard",
    "email": "Donec.elementum@scelerisquescelerisquedui.net",
    "phone": "00000004"
  },
  {
    "id": 14,
    "name": "Alec Howard",
    "email": "Donec.elementum@scelerisquescelerisquedui.net",
    "phone": "00000004"
  },
  {
    "id": 15,
    "name": "Alec Howard",
    "email": "Donec.elementum@scelerisquescelerisquedui.net",
    "phone": "00000004"
  },
  {
    "id": 16,
    "name": "Alec Howard",
    "email": "Donec.elementum@scelerisquescelerisquedui.net",
    "phone": "00000004"
  },
  {
    "id": 18,
    "name": "Alec Howard",
    "email": "Donec.elementum@scelerisquescelerisquedui.net",
    "phone": "00000004"
  },
  {
    "id": 16,
    "name": "Alec Howard",
    "email": "Donec.elementum@scelerisquescelerisquedui.net",
    "phone": "00000005"
  },
  {
    "id": 17,
    "name": "Alec Howard",
    "email": "Donec.elementum@scelerisquescelerisquedui.net",
    "phone": "123456789"
  },
  {
    "id": 18
  },
  {
    "id": 19,
    "name": "Alec Howard",
    "email": "Donec.elementum@scelerisquescelerisquedui.net"
  },
  {
    "id": 20,
    "name": "Alec Howard",
    "email": "Donec.elementum@scelerisquescelerisquedui.net",
    "phone": "123456789"
  },
  {
    "id": 21
  },
  {
    "id": 22
  },
  {
    "id": 23
  },
  {
    "id": 24,
    "name": "Alec Howard",
    "email": "Donec.elementum@scelerisquescelerisquedui.net",
    "phone": "123456789"
  },
  {
    "id": 25,
    "name": "Alec Howard",
    "email": "Donec.elementum@scelerisquescelerisquedui.net",
    "phone": "123456789"
  },
  {
    "id": 29,
    "name": "Alec Howard",
    "email": "Donec.elementum@scelerisquescelerisquedui.net",
    "phone": "123456789"
  }
]